[{"id":1,"message":"efewfwef","title":"tento vymazem","author":"wefwef","deleted":true,"creation_date":"12.10.18","tags":["martin jakubec"]},{"id":2,"message":"wefwef","title":"fwefwe","author":"wefwef","deleted":true,"creation_date":"12.10.18","tags":null},{"id":3,"message":"wefwefwef","title":"tento tu bude a basta","author":"sdff","deleted":true,"creation_date":"12.10.18","tags":null},{"id":4,"message":"fwefwefw","title":"wefwef","author":"wefwe","deleted":true,"creation_date":"12.10.18","tags":null},{"id":5,"message":"efwef","title":"wefwefw","author":"wefwef","deleted":true,"creation_date":"12.10.18","tags":null},{"id":6,"message":"fwefwef","title":"ewfwef","author":"wefwe","deleted":true,"creation_date":"12.10.18","tags":null},{"id":7,"message":"dqwdqwdq","title":"dqwdq","author":"dwqdqw","deleted":true,"creation_date":"12.10.18","tags":null},{"id":8,"message":"fwefwefw","title":"wefwef","author":"wefwe","deleted":true,"creation_date":"12.10.18","tags":null},{"id":9,"message":"efwefwef","title":"ewfwe","author":"fwefw","deleted":true,"creation_date":"12.10.18","tags":null},{"id":10,"message":"wefwef","title":"ewef","author":"ewfwef","deleted":true,"creation_date":"12.10.18","tags":null},{"id":11,"message":"wefewfwe","title":"ewfwef","author":"wefwefwfe","deleted":true,"creation_date":"12.10.18","tags":null},{"id":12,"message":"fwefwef","title":"efwefwe","author":"fwefwe","deleted":true,"creation_date":"12.10.18","tags":["jedlo","moda","martin jakubec"]},{"id":13,"message":"werwer","title":"werwe","author":"werwer","deleted":true,"creation_date":"12.10.18","tags":null}]